README.md
setup.cfg
setup.py
sofi/__init__.py
sofi.egg-info/PKG-INFO
sofi.egg-info/SOURCES.txt
sofi.egg-info/dependency_links.txt
sofi.egg-info/requires.txt
sofi.egg-info/top_level.txt
sofi/app/__init__.py
sofi/app/_sofi.js
sofi/app/app.py
sofi/app/main.html
sofi/ui/__init__.py
sofi/ui/abbreviation.py
sofi/ui/address.py
sofi/ui/alert.py
sofi/ui/alertlink.py
sofi/ui/anchor.py
sofi/ui/badge.py
sofi/ui/basicblock.py
sofi/ui/blockquote.py
sofi/ui/bold.py
sofi/ui/button.py
sofi/ui/buttondropdown.py
sofi/ui/buttongroup.py
sofi/ui/buttontoolbar.py
sofi/ui/cite.py
sofi/ui/code.py
sofi/ui/column.py
sofi/ui/container.py
sofi/ui/deleted.py
sofi/ui/description.py
sofi/ui/descriptiondefinition.py
sofi/ui/descriptionterm.py
sofi/ui/div.py
sofi/ui/dropdown.py
sofi/ui/dropdownitem.py
sofi/ui/element.py
sofi/ui/fontawesomeicon.py
sofi/ui/footer.py
sofi/ui/form.py
sofi/ui/formgroup.py
sofi/ui/heading.py
sofi/ui/image.py
sofi/ui/input.py
sofi/ui/inserted.py
sofi/ui/italics.py
sofi/ui/jumbotron.py
sofi/ui/label.py
sofi/ui/listgroup.py
sofi/ui/listitem.py
sofi/ui/mark.py
sofi/ui/navbar.py
sofi/ui/navbaritem.py
sofi/ui/orderedlist.py
sofi/ui/pageheader.py
sofi/ui/panel.py
sofi/ui/paragraph.py
sofi/ui/row.py
sofi/ui/sample.py
sofi/ui/small.py
sofi/ui/span.py
sofi/ui/strikethrough.py
sofi/ui/table.py
sofi/ui/tablebody.py
sofi/ui/tablecell.py
sofi/ui/tablefooter.py
sofi/ui/tablehead.py
sofi/ui/tablerow.py
sofi/ui/textarea.py
sofi/ui/underlined.py
sofi/ui/unorderedlist.py
sofi/ui/userinput.py
sofi/ui/variable.py
sofi/ui/view.py
sofi/ui/well.py