Metadata-Version: 2.1
Name: sofi
Version: 0.3.8
Summary: Desktop and Web GUI framework based on WebSockets
Home-page: https://github.com/tryexceptpass/sofi
Author: tryexceptpass
Author-email: cmedina@tryexceptpass.org
License: MIT
Project-URL: Gitter Chat, https://gitter.im/try-except-pass/sofi
Project-URL: Say Thanks!, https://saythanks.io/to/tryexceptpass
Project-URL: Source, https://github.com/tryexceptpass/sofi
Project-URL: Documentation, http://sofi-gui-framework.readthedocs.io/en/latest/
Keywords: websockets javascript bootstrap gui unity3d desktop html
Platform: UNKNOWN
Classifier: License :: OSI Approved :: MIT License
Classifier: Framework :: AsyncIO
Classifier: Topic :: Internet :: WWW/HTTP
Classifier: Topic :: Internet :: WWW/HTTP :: Dynamic Content
Classifier: Topic :: Multimedia
Classifier: Topic :: Multimedia :: Graphics
Classifier: Topic :: Software Development :: User Interfaces
Classifier: Programming Language :: Python :: 3 :: Only
Classifier: Programming Language :: Python :: 3.6
Classifier: Development Status :: 4 - Beta
Requires-Python: >=3.6
